vemseg/__init__.py
vemseg/_utils.py
vemseg/_vem_classifier.py
vemseg-0.0.3.dist-info/LICENSE
vemseg-0.0.3.dist-info/METADATA
vemseg-0.0.3.dist-info/WHEEL
vemseg-0.0.3.dist-info/top_level.txt
vemseg-0.0.3.dist-info/RECORD
