Metadata-Version: 2.1
Name: vemseg
Version: 0.0.3
Summary: A python package for the segmentation of organelles in volume electron microscopy data
Home-page: https://github.com/MatousE/vemseg
Author: MatousE
Author-email: matous.elphick@gmail.com
License: BSD 3-Clause License
License-File: LICENSE
Requires-Dist: numpy
Requires-Dist: apoc
Requires-Dist: scipy
Requires-Dist: scikit-image
Requires-Dist: scikit-learn
Requires-Dist: matplotlib
Requires-Dist: xgboost
Requires-Dist: setuptools
